fletcher/__init__.py
fletcher/_version.py
fletcher/fletcher.py
fletcher_maximus-0.0.6.dist-info/LICENSE
fletcher_maximus-0.0.6.dist-info/METADATA
fletcher_maximus-0.0.6.dist-info/WHEEL
fletcher_maximus-0.0.6.dist-info/top_level.txt
fletcher_maximus-0.0.6.dist-info/RECORD
