Metadata-Version: 2.1
Name: fletcher_maximus
Version: 0.0.6
Summary: A package for quickly spotting molecular geometric features in protein structural files.
Author-email: Jon Agirre <jon.agirre@york.ac.uk>, Federico Sabbadin <federico.sabbadin@york.ac.uk>
Maintainer-email: Jon Agirre <jon.agirre@york.ac.uk>
Project-URL: Homepage, https://github.com/glycojones/fletcher
Project-URL: Issues, https://github.com/glycojones/fletcher/issues
Classifier: License :: OSI Approved :: MIT License
Classifier: Operating System :: OS Independent
Classifier: Programming Language :: Python :: 3.8
Requires-Python: >=3.8
License-File: LICENSE
Requires-Dist: gemmi>=0.6.6
